.gitignore
.travis.yml
LICENSE
MANIFEST.in
README.md
changelog.md
clonevirtualenv.py
setup.py
tox.ini
clone_env.egg-info/PKG-INFO
clone_env.egg-info/SOURCES.txt
clone_env.egg-info/dependency_links.txt
clone_env.egg-info/entry_points.txt
clone_env.egg-info/top_level.txt
tests/__init__.py
tests/test_dirmatch.py
tests/test_fixup_scripts.py
tests/test_virtualenv_clone.py
tests/test_virtualenv_sys.py